general_conference_extractor/GeneralConferenceTalk.py
general_conference_extractor/__init__.py
general_conference_extractor/_modidx.py
general_conference_extractor/core.py
general_conference_extractor/data_output.py
general_conference_extractor/extractURLs.py
general_conference_extractor/extract_URLs.py
general_conference_extractor-0.0.1.dist-info/LICENSE
general_conference_extractor-0.0.1.dist-info/METADATA
general_conference_extractor-0.0.1.dist-info/WHEEL
general_conference_extractor-0.0.1.dist-info/entry_points.txt
general_conference_extractor-0.0.1.dist-info/top_level.txt
general_conference_extractor-0.0.1.dist-info/RECORD
