Metadata-Version: 2.1
Name: general-conference-extractor
Version: 0.0.1
Summary: This library allows you to extract all the speeches given for the general conferences of the Church of Jesus Christ of Latter-Day Saints from April 1971 to the most recent month and year.
Home-page: https://github.com/c-a-s-t-l-e/general-conference-extractor
Author: c-a-s-t-l-e
Author-email: castle676767@gmail.com
License: Apache Software License 2.0
Keywords: nbdev jupyter notebook python
Platform: UNKNOWN
Classifier: Development Status :: 4 - Beta
Classifier: Intended Audience :: Developers
Classifier: Natural Language :: English
Classifier: Programming Language :: Python :: 3.7
Classifier: Programming Language :: Python :: 3.8
Classifier: Programming Language :: Python :: 3.9
Classifier: Programming Language :: Python :: 3.10
Classifier: License :: OSI Approved :: Apache Software License
Requires-Python: >=3.7
License-File: LICENSE
Requires-Dist: bs4
Requires-Dist: fastcore
Requires-Dist: pandas
Requires-Dist: requests
Provides-Extra: dev
